lms_control/__about__.py
lms_control/__init__.py
lms_control/cli.py
lms_control/exc.py
lms_control/player.py
lms_control/server.py
lms_control-0.0.1.dist-info/METADATA
lms_control-0.0.1.dist-info/WHEEL
lms_control-0.0.1.dist-info/entry_points.txt
lms_control-0.0.1.dist-info/licenses/LICENSE.txt
lms_control-0.0.1.dist-info/RECORD
