Metadata-Version: 2.4
Name: lms-control
Version: 0.0.1
Summary: Command Line Toolkit to Control LMS Player
Project-URL: Documentation, https://github.com/pschleiter/lms-control#readme
Project-URL: Issues, https://github.com/pschleiter/lms-control/issues
Project-URL: Source, https://github.com/pschleiter/lms-control
Author-email: Patrick Schleiter <git.pschleiter@gmail.com>
License-Expression: MIT
License-File: LICENSE.txt
Classifier: Development Status :: 4 - Beta
Classifier: Programming Language :: Python
Classifier: Programming Language :: Python :: 3.10
Classifier: Programming Language :: Python :: 3.11
Classifier: Programming Language :: Python :: 3.12
Classifier: Programming Language :: Python :: Implementation :: CPython
Classifier: Programming Language :: Python :: Implementation :: PyPy
Requires-Python: >=3.10
Requires-Dist: click
Requires-Dist: httpx
